[
  {
    "ContainingType": "Program\u002B\u003C\u003Ec__DisplayClass0_0",
    "Method": "\u003C\u003CMain\u003E$\u003Eb__0",
    "RelativePath": "api/products",
    "HttpMethod": "GET",
    "IsController": false,
    "Order": 0,
    "Parameters": [],
    "ReturnTypes": [
      {
        "Type": "System.Void",
        "MediaTypes": [],
        "StatusCode": 200
      }
    ],
    "EndpointName": "GetProducts"
  },
  {
    "ContainingType": "Program\u002B\u003C\u003Ec__DisplayClass0_0",
    "Method": "\u003C\u003CMain\u003E$\u003Eb__2",
    "RelativePath": "api/products",
    "HttpMethod": "POST",
    "IsController": false,
    "Order": 0,
    "Parameters": [
      {
        "Name": "dto",
        "Type": "ProductCreateDto",
        "IsRequired": true
      }
    ],
    "ReturnTypes": [
      {
        "Type": "System.Void",
        "MediaTypes": [],
        "StatusCode": 200
      }
    ],
    "EndpointName": "CreateProduct"
  },
  {
    "ContainingType": "Program\u002B\u003C\u003Ec__DisplayClass0_0",
    "Method": "\u003C\u003CMain\u003E$\u003Eb__1",
    "RelativePath": "api/products/{id:guid}",
    "HttpMethod": "GET",
    "IsController": false,
    "Order": 0,
    "Parameters": [
      {
        "Name": "id",
        "Type": "System.Guid",
        "IsRequired": true
      }
    ],
    "ReturnTypes": [
      {
        "Type": "System.Void",
        "MediaTypes": [],
        "StatusCode": 200
      }
    ],
    "EndpointName": "GetProductById"
  },
  {
    "ContainingType": "Program\u002B\u003C\u003Ec__DisplayClass0_0",
    "Method": "\u003C\u003CMain\u003E$\u003Eb__3",
    "RelativePath": "api/products/{id:guid}",
    "HttpMethod": "DELETE",
    "IsController": false,
    "Order": 0,
    "Parameters": [
      {
        "Name": "id",
        "Type": "System.Guid",
        "IsRequired": true
      }
    ],
    "ReturnTypes": [
      {
        "Type": "System.Void",
        "MediaTypes": [],
        "StatusCode": 200
      }
    ],
    "EndpointName": "DeleteProduct"
  },
  {
    "ContainingType": "Program\u002B\u003C\u003Ec__DisplayClass0_0",
    "Method": "\u003C\u003CMain\u003E$\u003Eb__4",
    "RelativePath": "weatherforecast",
    "HttpMethod": "GET",
    "IsController": false,
    "Order": 0,
    "Parameters": [],
    "ReturnTypes": [
      {
        "Type": "WeatherForecast[]",
        "MediaTypes": [
          "application/json"
        ],
        "StatusCode": 200
      }
    ],
    "EndpointName": "GetWeatherForecast"
  }
]